{
	"cmake" : 
	{
		"generator" : 
		{
			"multiConfig" : false,
			"name" : "Unix Makefiles"
		},
		"paths" : 
		{
			"cmake" : "/usr/bin/cmake",
			"cpack" : "/usr/bin/cpack",
			"ctest" : "/usr/bin/ctest",
			"root" : "/usr/share/cmake-3.20"
		},
		"version" : 
		{
			"isDirty" : false,
			"major" : 3,
			"minor" : 20,
			"patch" : 0,
			"string" : "3.20.0",
			"suffix" : ""
		}
	},
	"objects" : 
	[
		{
			"jsonFile" : "codemodel-v2-8939a94f54bc4c24df24.json",
			"kind" : "codemodel",
			"version" : 
			{
				"major" : 2,
				"minor" : 2
			}
		},
		{
			"jsonFile" : "cache-v2-a3a2a6aaed319d0b73e1.json",
			"kind" : "cache",
			"version" : 
			{
				"major" : 2,
				"minor" : 0
			}
		},
		{
			"jsonFile" : "cmakeFiles-v1-ed69c3cfc3d8254717e0.json",
			"kind" : "cmakeFiles",
			"version" : 
			{
				"major" : 1,
				"minor" : 0
			}
		}
	],
	"reply" : 
	{
		"cache-v2" : 
		{
			"jsonFile" : "cache-v2-a3a2a6aaed319d0b73e1.json",
			"kind" : "cache",
			"version" : 
			{
				"major" : 2,
				"minor" : 0
			}
		},
		"cmakeFiles-v1" : 
		{
			"jsonFile" : "cmakeFiles-v1-ed69c3cfc3d8254717e0.json",
			"kind" : "cmakeFiles",
			"version" : 
			{
				"major" : 1,
				"minor" : 0
			}
		},
		"codemodel-v2" : 
		{
			"jsonFile" : "codemodel-v2-8939a94f54bc4c24df24.json",
			"kind" : "codemodel",
			"version" : 
			{
				"major" : 2,
				"minor" : 2
			}
		}
	}
}
